jaquar/__init__.py
jaquar/cli.py
jaquar/templates/config/__init__.py
jaquar/templates/config/settings.py
jaquar/templates/config/urls.py
jaquar/templates/db/__init__.py
jaquar/templates/db/schema.py
jaquar/templates/models/__init__.py
jaquar/templates/models/models.py
jaquar/templates/templates/index.html.jq
jaquar/templates/views/__init__.py
jaquar/templates/views/about.py
jaquar/templates/views/contact.py
jaquar/templates/views/home.py
jaquar/templates/views/index.py
jaquar-0.6.4.dist-info/METADATA
jaquar-0.6.4.dist-info/WHEEL
jaquar-0.6.4.dist-info/entry_points.txt
jaquar-0.6.4.dist-info/top_level.txt
jaquar-0.6.4.dist-info/RECORD
